LICENSE
MANIFEST.in
setup.py
version.py
rask_njord_mercadopago/__init__.py
rask_njord_mercadopago.egg-info/PKG-INFO
rask_njord_mercadopago.egg-info/SOURCES.txt
rask_njord_mercadopago.egg-info/dependency_links.txt
rask_njord_mercadopago.egg-info/requires.txt
rask_njord_mercadopago.egg-info/top_level.txt