Metadata-Version: 1.0
Name: rask-njord-mercadopago
Version: 0.5.2
Summary: Rask MercadoPago Connector
Home-page: https://gitlab.com/vikingmakt/rask_njord_mercadopago
Author: Guilherme Nemeth
Author-email: guilherme@vikingmakt.com.br
License: https://gitlab.com/vikingmakt/rask_njord_mercadopago/raw/master/LICENSE
Platform: UNKNOWN
